p5250/__init__.py
p5250-0.1.0.dist-info/LICENSE.txt
p5250-0.1.0.dist-info/METADATA
p5250-0.1.0.dist-info/WHEEL
p5250-0.1.0.dist-info/top_level.txt
p5250-0.1.0.dist-info/RECORD
