Metadata-Version: 2.1
Name: p5250
Version: 0.1.0
Summary: Python library to communicate with IBM i hosts, based on the 5250 protocol. For example AS400.
Home-page: https://github.com/simonfaltum/p5250
Author: Simon Faltum
License: UNKNOWN
Keywords: IBM AS400 IBMi TN5250 Mainframe
Platform: UNKNOWN
Classifier: Intended Audience :: Developers
Classifier: Programming Language :: Python
Classifier: Programming Language :: Python :: 3
Classifier: Programming Language :: Python :: 3 :: Only
Classifier: Operating System :: Unix
Classifier: Operating System :: POSIX :: Linux
Classifier: Topic :: Software Development :: Testing
Classifier: Topic :: Software Development :: Libraries :: Python Modules
Classifier: License :: OSI Approved :: GNU General Public License v3 (GPLv3)
Classifier: Development Status :: 4 - Beta
Requires-Python: >=3.6
Requires-Dist: p3270 (>=0.1.3)
